[
	{
		"id":"01",
		"title":"intro",
		"classroom_id":"1",
		"classroom_code":"MATH7K345",
		"duration":"",
		"slide_id":"",
		"type":"1",
		"video_url":"private_set/01.ogv"
	},
	{
		"id":"02",
		"title":"drill1",
		"classroom_id":"1",
		"classroom_code":"MATH7K345",
		"duration":"",
		"slide_id":"",
		"type":"2",
		"video_url":"private_set/02.ogv"
	},
	{
		"id":"03",
		"title":"drill2",
		"classroom_id":"1",
		"classroom_code":"MATH7K345",
		"duration":"",
		"slide_id":"",
		"type":"2",
		"video_url":"private_set/03.ogv"
	}
]